owl_builder/__init__.py
owl_builder/builder/__init__.py
owl_builder/builder/dmo/__init__.py
owl_builder/builder/svc/__init__.py
owl_builder/builder/svc/generate_intent_name.py
owl_builder/builder/svc/generate_qa_pairs.py
owl_builder/builder/svc/generate_ttl_node.py
owl_builder/core/__init__.py
owl_builder/core/openai_cache.py
owl_builder/keyterms/__init__.py
owl_builder/keyterms/bp/__init__.py
owl_builder/keyterms/bp/autotaxo_orchestrator.py
owl_builder/keyterms/dmo/__init__.py
owl_builder/keyterms/dmo/openai_keyterm_extractor.py
owl_builder/keyterms/dmo/stopword_filter.py
owl_builder/keyterms/dmo/textacy_keyterm_extractor.py
owl_builder/keyterms/dmo/textacy_ngram_extractor.py
owl_builder/keyterms/dmo/textacy_nounchunk_extractor.py
owl_builder/keyterms/dmo/textacy_term_extractor.py
owl_builder/keyterms/dmo/textacy_triple_extractor.py
owl_builder/keyterms/dto/__init__.py
owl_builder/keyterms/dto/spacy_model.py
owl_builder/keyterms/dto/stopwords_kb.py
owl_builder/keyterms/README.md
owl_builder/keyterms/svc/__init__.py
owl_builder/keyterms/svc/extract_keyterms.py
owl_builder/keyterms/svc/filter_keyterms.py
owl_builder/keyterms/svc/generate_taxonomy_dataframe.py
owl_builder/keyterms/svc/generate_taxonomy_ttl.py
owl_builder/recipes/recipe_for_intent_mapping.py
owl_builder/relationships/__init__.py
owl_builder/relationships/bp/__init__.py
owl_builder/relationships/bp/autorels_orchestrator.py
owl_builder/relationships/README.md
owl_builder/relationships/svc/__init__.py
owl_builder/relationships/svc/find_implies_relationships.py
owl_builder/relationships/svc/find_requires_relationships.py
owl_builder/relationships/svc/generate_relationships_ttl.py
owl_builder/synonyms/__init__.py
owl_builder/synonyms/bp/__init__.py
owl_builder/synonyms/dmo/__init__.py
owl_builder/synonyms/dmo/openai_cache_writer.py
owl_builder/synonyms/dmo/openai_event_executor.py
owl_builder/synonyms/dmo/openai_output_extractor.py
owl_builder/synonyms/dmo/synonym_prompt_generator.py
owl_builder-0.2.3.dist-info/METADATA
owl_builder-0.2.3.dist-info/WHEEL
owl_builder-0.2.3.dist-info/RECORD
