Metadata-Version: 2.1
Name: owl-builder
Version: 0.2.3
Summary: Tools for Automating the Construction of an Ontology (OWL)
Home-page: https://github.com/craigtrim/owl-builder
License: None
Keywords: nlp,nlu,ai,ontology,automation
Author: Craig Trim
Author-email: craigtrim@gmail.com
Maintainer: Craig Trim
Maintainer-email: craigtrim@gmail.com
Requires-Python: >=3.8.5,<4.0.0
Classifier: Development Status :: 4 - Beta
Classifier: License :: Other/Proprietary License
Classifier: Programming Language :: Python :: 3
Classifier: Programming Language :: Python :: 3.9
Classifier: Programming Language :: Python :: 3.10
Classifier: Programming Language :: Python :: 3.11
Classifier: Topic :: Scientific/Engineering :: Artificial Intelligence
Classifier: Topic :: Software Development :: Libraries :: Python Modules
Requires-Dist: baseblock
Requires-Dist: networkx (==2.8.8)
Requires-Dist: nltk (==3.8.1)
Requires-Dist: openai (>=0.27.0,<0.28.0)
Requires-Dist: openai_helper
Requires-Dist: pandas (>=1.4.0,<2.0.0)
Requires-Dist: rdflib (>=6.1.1,<7.0.0)
Requires-Dist: regex (==2022.7.9)
Requires-Dist: scipy (==1.9.2)
Requires-Dist: spacy (==3.5.3)
Requires-Dist: tabulate
Requires-Dist: textacy (==0.12.0)
Requires-Dist: textblob (>=0.17.1,<0.18.0)
Project-URL: Repository, https://github.com/craigtrim/owl-builder
